aiverify/__init__.py
aiverify-0.1.0.dist-info/METADATA
aiverify-0.1.0.dist-info/WHEEL
aiverify-0.1.0.dist-info/RECORD
