Metadata-Version: 2.1
Name: aiverify
Version: 0.1.0
Summary: 
Author: CachCheng
Author-email: tkggpdc2007@163.com
Requires-Python: >=3.8,<4.0
Classifier: Programming Language :: Python :: 3
Classifier: Programming Language :: Python :: 3.8
Classifier: Programming Language :: Python :: 3.9
Classifier: Programming Language :: Python :: 3.10
Classifier: Programming Language :: Python :: 3.11
Classifier: Programming Language :: Python :: 3.12
Requires-Dist: cryptography (>=42.0.5,<43.0.0)
Requires-Dist: requests (>=2.31.0,<3.0.0)
